dissononce/__init__.py
dissononce/cipher/__init__.py
dissononce/cipher/aesgcm.py
dissononce/cipher/chachapoly.py
dissononce/cipher/cipher.py
dissononce/dh/__init__.py
dissononce/dh/dh.py
dissononce/dh/keypair.py
dissononce/dh/private.py
dissononce/dh/public.py
dissononce/dh/x25519/__init__.py
dissononce/dh/x25519/keypair.py
dissononce/dh/x25519/private.py
dissononce/dh/x25519/public.py
dissononce/dh/x25519/x25519.py
dissononce/dh/x448/__init__.py
dissononce/dh/x448/keypair.py
dissononce/dh/x448/private.py
dissononce/dh/x448/public.py
dissononce/dh/x448/x448.py
dissononce/exceptions/__init__.py
dissononce/exceptions/decrypt.py
dissononce/extras/__init__.py
dissononce/extras/cipher/__init__.py
dissononce/extras/cipher/dangerous/__init__.py
dissononce/extras/cipher/experimental/__init__.py
dissononce/extras/dh/__init__.py
dissononce/extras/dh/dangerous/__init__.py
dissononce/extras/dh/dangerous/dh_nogen.py
dissononce/extras/dh/experimental/__init__.py
dissononce/extras/hash/__init__.py
dissononce/extras/hash/dangerous/__init__.py
dissononce/extras/hash/experimental/__init__.py
dissononce/extras/meta/__init__.py
dissononce/extras/meta/cipher/__init__.py
dissononce/extras/meta/cipher/factory.py
dissononce/extras/meta/dh/__init__.py
dissononce/extras/meta/dh/factory.py
dissononce/extras/meta/hash/__init__.py
dissononce/extras/meta/hash/factory.py
dissononce/extras/meta/modifier/__init__.py
dissononce/extras/meta/modifier/factory.py
dissononce/extras/meta/pattern/__init__.py
dissononce/extras/meta/pattern/factory.py
dissononce/extras/meta/protocol/__init__.py
dissononce/extras/meta/protocol/factory.py
dissononce/extras/meta/protocol/protocol.py
dissononce/extras/processing/__init__.py
dissononce/extras/processing/handshakestate_forwarder.py
dissononce/extras/processing/handshakestate_guarded.py
dissononce/extras/processing/handshakestate_switchable.py
dissononce/hash/__init__.py
dissononce/hash/blake2b.py
dissononce/hash/blake2s.py
dissononce/hash/hash.py
dissononce-0.34.3.dist-info/LICENSE
dissononce-0.34.3.dist-info/METADATA
dissononce-0.34.3.dist-info/WHEEL
dissononce-0.34.3.dist-info/top_level.txt
dissononce-0.34.3.dist-info/RECORD
